CHANGELOG.md
LICENSE.txt
MANIFEST.in
README.md
daemoncmd.py
setup.py
daemoncmd.egg-info/PKG-INFO
daemoncmd.egg-info/SOURCES.txt
daemoncmd.egg-info/dependency_links.txt
daemoncmd.egg-info/entry_points.txt
daemoncmd.egg-info/top_level.txt