Metadata-Version: 1.1
Name: daemoncmd
Version: 0.2.0
Summary: Turn any command line into a daemon with a pidfile and start, stop, restart, and status commands.
Home-page: https://github.com/todddeluca/daemoncmd
Author: Todd Francis DeLuca
Author-email: todddeluca@yahoo.com
License: MIT
Keywords: daemon python cli init nohup commandline executable script pidfile
Platform: UNKNOWN
Classifier: License :: OSI Approved :: MIT License
Classifier: Development Status :: 3 - Alpha
Classifier: Programming Language :: Python :: 2
Classifier: Programming Language :: Python :: 2.7
